apple_store_scraper/__init__.py
apple_store_scraper/__version__.py
apple_store_scraper/app_store.py
apple_store_scraper/base.py
apple_store_scraper/podcast.py
apple_store_scraper-0.3.6.dist-info/LICENCE
apple_store_scraper-0.3.6.dist-info/METADATA
apple_store_scraper-0.3.6.dist-info/WHEEL
apple_store_scraper-0.3.6.dist-info/top_level.txt
apple_store_scraper-0.3.6.dist-info/RECORD
