Metadata-Version: 2.1
Name: apple-store-scraper
Version: 0.3.6
Summary: Single API ☝ App Store Review Scraper 🧹
Home-page: https://github.com/hiyali/apple-store-scraper
Author: Eric Lim
License: MIT
Project-URL: Source, https://github.com/hiyali/apple-store-scraper
Keywords: app store,ios,ios apps,podcasts,review,scraping,scraper
Classifier: Intended Audience :: Developers
Classifier: License :: OSI Approved :: MIT License
Classifier: Natural Language :: English
Classifier: Operating System :: OS Independent
Classifier: Programming Language :: Python :: 3
Classifier: Programming Language :: Python :: 3.9
Classifier: Programming Language :: Python :: 3.10
Classifier: Topic :: Internet :: WWW/HTTP
Classifier: Topic :: Scientific/Engineering :: Information Analysis
Requires-Python: >=3.9
License-File: LICENCE
Requires-Dist: requests (==2.25.1)
